microcosm_resourcesync/__init__.py
microcosm_resourcesync/batching.py
microcosm_resourcesync/following.py
microcosm_resourcesync/main.py
microcosm_resourcesync/toposort.py
microcosm_resourcesync/endpoints/__init__.py
microcosm_resourcesync/endpoints/base.py
microcosm_resourcesync/endpoints/directory_endpoint.py
microcosm_resourcesync/endpoints/http_endpoint.py
microcosm_resourcesync/endpoints/null_endpoint.py
microcosm_resourcesync/endpoints/pipe_endpoint.py
microcosm_resourcesync/endpoints/yaml_file_endpoint.py
microcosm_resourcesync/formatters/__init__.py
microcosm_resourcesync/formatters/base.py
microcosm_resourcesync/formatters/json_formatter.py
microcosm_resourcesync/formatters/yaml_formatter.py
microcosm_resourcesync/schemas/__init__.py
microcosm_resourcesync/schemas/base.py
microcosm_resourcesync/schemas/hal_schema.py
microcosm_resourcesync/schemas/simple_schema.py
microcosm_resourcesync-2.0.0.dist-info/LICENSE
microcosm_resourcesync-2.0.0.dist-info/METADATA
microcosm_resourcesync-2.0.0.dist-info/WHEEL
microcosm_resourcesync-2.0.0.dist-info/entry_points.txt
microcosm_resourcesync-2.0.0.dist-info/top_level.txt
microcosm_resourcesync-2.0.0.dist-info/RECORD
